ast_tools/__init__.py
ast_tools/common.py
ast_tools/immutable_ast.py
ast_tools/macros.py
ast_tools/pattern.py
ast_tools/stack.py
ast_tools/utils.py
ast_tools/cst_utils/__init__.py
ast_tools/cst_utils/deep_node.py
ast_tools/cst_utils/insert_statements.py
ast_tools/metadata/__init__.py
ast_tools/metadata/always_returns_provider.py
ast_tools/metadata/condition_provider.py
ast_tools/passes/__init__.py
ast_tools/passes/base.py
ast_tools/passes/bool_to_bit.py
ast_tools/passes/cse.py
ast_tools/passes/debug.py
ast_tools/passes/if_inline.py
ast_tools/passes/if_to_phi.py
ast_tools/passes/loop_unroll.py
ast_tools/passes/remove_asserts.py
ast_tools/passes/ssa.py
ast_tools/passes/util.py
ast_tools/transformers/__init__.py
ast_tools/transformers/if_inliner.py
ast_tools/transformers/loop_unroller.py
ast_tools/transformers/node_replacer.py
ast_tools/transformers/node_tracker.py
ast_tools/transformers/normalizers.py
ast_tools/transformers/renamer.py
ast_tools/transformers/symbol_replacer.py
ast_tools/visitors/__init__.py
ast_tools/visitors/collect_names.py
ast_tools/visitors/collect_targets.py
ast_tools/visitors/node_finder.py
ast_tools/visitors/used_names.py
ast_tools-0.1.8.dist-info/METADATA
ast_tools-0.1.8.dist-info/WHEEL
ast_tools-0.1.8.dist-info/top_level.txt
ast_tools-0.1.8.dist-info/RECORD
