Metadata-Version: 2.1
Name: ast-tools
Version: 0.1.8
Summary: Toolbox for working with the Python AST
Home-page: https://github.com/leonardt/ast_tools
Author: Leonard Truong
Author-email: lenny@cs.stanford.edu
License: UNKNOWN
Platform: UNKNOWN
Requires-Dist: astor
Requires-Dist: libcst
